poweroperator/__init__.py
poweroperator/cli.py
poweroperator/local_module_indexer.py
poweroperator/poweroperator_api.py
poweroperator-0.0.6.dist-info/METADATA
poweroperator-0.0.6.dist-info/WHEEL
poweroperator-0.0.6.dist-info/entry_points.txt
poweroperator-0.0.6.dist-info/top_level.txt
poweroperator-0.0.6.dist-info/RECORD
