Metadata-Version: 2.4
Name: poweroperator
Version: 0.0.6
Summary: The most productive dev stack ever
Author-email: Michael Bacarella <michael@poweroperator.com>, Paul Roales <paul@poweroperator.com>
Project-URL: homepage, https://poweroperator.com
Classifier: Programming Language :: Python :: 3
Classifier: License :: OSI Approved :: MIT License
Classifier: Operating System :: OS Independent
Requires-Python: >=3.8.1
Requires-Dist: requests>=2.32.3
Requires-Dist: scalene>=1.5.51
Requires-Dist: rich>=10.7.0
Requires-Dist: cloudpickle>=2.2.1
Requires-Dist: Jinja2>=3.0.3
Requires-Dist: psutil>=5.9.2
Requires-Dist: astunparse>=1.6.3; python_version < "3.9"
Requires-Dist: numpy!=1.27,>=1.24.0
Requires-Dist: pydantic>=2.6
